hollyscroll.py
hollyscroll-1.2.2.dist-info/METADATA
hollyscroll-1.2.2.dist-info/WHEEL
hollyscroll-1.2.2.dist-info/entry_points.txt
hollyscroll-1.2.2.dist-info/licenses/LICENSE
hollyscroll-1.2.2.dist-info/RECORD
