Metadata-Version: 2.1
Name: hollyscroll
Version: 1.2.2
Summary: Scroll text on the terminal screen like in movies
Project-URL: Homepage, https://github.com/sumpygump/hollyscroll
Project-URL: Bug Tracker, https://github.com/sumpygump/hollyscroll/issues
Author-email: Jansen Price <jansen.price@gmail.com>
License-File: LICENSE
Classifier: License :: OSI Approved :: MIT License
Classifier: Operating System :: OS Independent
Classifier: Programming Language :: Python :: 3
Requires-Python: >=3.7
